autorater/__init__.py
autorater-0.0.34.dist-info/METADATA
autorater-0.0.34.dist-info/WHEEL
autorater-0.0.34.dist-info/licenses/LICENSE
autorater-0.0.34.dist-info/RECORD
